marsel/__init__.py
marsel/_redis.py
marsel/core.py
marsel-0.1.1.dist-info/METADATA
marsel-0.1.1.dist-info/WHEEL
marsel-0.1.1.dist-info/licenses/LICENSE
marsel-0.1.1.dist-info/RECORD
